[
  {
    "Id": "1c61f827-a977-4285-b481-f767508deab3",
    "Username": "isa",
    "PasswordHash": "AXc10JToCSAD7zB\u002BjhM\u002BS7PtDBI/x5eUkxVCRH3lnnyQOw\u002BP0u6ilTNDaeKi5lPa0w==",
    "FullName": "Isabela Santos",
    "Email": "isabela@email.com",
    "City": "S\u00E3o Vicentre",
    "State": "S\u00E3o Paulo",
    "Address": "Rua Marqu\u00EAs de S\u00E3o Vicente, 410, Parque Bitaru, S\u00E3o Vicente, S\u00E3o Paulo, Brasil",
    "Latitude": null,
    "Longitude": null,
    "Preferences": {},
    "CreatedAt": "2025-11-13T17:35:45.5914575Z"
  },
  {
    "Id": "b04b1adb-925b-41a4-a351-559e3ba6e6ac",
    "Username": "Pedro",
    "PasswordHash": "AayX3Mv8QKVkTwV9CE8cvHsf4jFptZyH7maCgNTg42k5b67EOzfgHDSnyiyEVl6EKw==",
    "FullName": "Pedro Salgado",
    "Email": "pedro@email.com",
    "City": "S\u00E3o Vicente",
    "State": "S\u00E3o Paulo",
    "Address": "Rua Marqu\u00EAs de S\u00E3o Vicente, 410, Parque Bitaru, S\u00E3o Vicente, S\u00E3o Paulo, Brasil",
    "Latitude": -239691947,
    "Longitude": -463965619,
    "Preferences": {},
    "CreatedAt": "2025-11-13T18:11:54.0902435Z"
  }
]